{
  "_class": "text",
  "attributedString": {
    "_class": "attributedString",
    "attributes": [
      {
        "_class": "stringAttribute",
        "attributes": {
          "MSAttributedStringColorAttribute": {
            "_class": "color",
            "alpha": 1,
            "blue": 1,
            "green": 1,
            "red": 1
          },
          "MSAttributedStringFontAttribute": {
            "_class": "fontDescriptor",
            "attributes": {
              "name": "OpenSans-Bold",
              "size": 18
            }
          },
          "paragraphStyle": {
            "_class": "paragraphStyle",
            "maximumLineHeight": 26,
            "minimumLineHeight": 26
          }
        },
        "length": 47,
        "location": 0
      }
    ],
    "string": "Bantu Biaya NICU Baby Hapsah agar sehat kembali"
  },
  "automaticallyDrawOnUnderlyingPath": false,
  "booleanOperation": 0,
  "clippingMaskMode": 0,
  "do_objectID": "674937A5-8B11-42F4-8951-1B62AE230FFC",
  "dontSynchroniseWithSymbol": false,
  "exportOptions": {
    "_class": "exportOptions",
    "do_objectID": "1D1CEA75-14FD-4937-81B1-49FD22AD4348",
    "exportFormats": [
    ],
    "includedLayerIds": [
    ],
    "layerOptions": 0,
    "shouldTrim": false
  },
  "frame": {
    "_class": "rect",
    "constrainProportions": false,
    "do_objectID": "7670E2AE-59CF-4946-8727-AB6898E27D56",
    "height": 26,
    "width": 459,
    "x": 47,
    "y": 434
  },
  "glyphBounds": "{{1, 6}, {455, 19}}",
  "hasClippingMask": false,
  "isFixedToViewport": false,
  "isFlippedHorizontal": false,
  "isFlippedVertical": false,
  "isLocked": false,
  "isVisible": true,
  "layerListExpandedType": 0,
  "lineSpacingBehaviour": 2,
  "name": "Bantu Biaya NICU Bab",
  "nameIsFixed": false,
  "resizingConstraint": 63,
  "resizingType": 0,
  "rotation": 0,
  "shouldBreakMaskChain": false,
  "style": {
    "_class": "style",
    "do_objectID": "19616F6C-D9D1-434C-B876-E7DDE8107562",
    "endMarkerType": 0,
    "miterLimit": 10,
    "startMarkerType": 0,
    "textStyle": {
      "_class": "textStyle",
      "do_objectID": "D8955788-9E24-4F56-A16C-20A28AE6BCF8",
      "encodedAttributes": {
        "MSAttributedStringColorAttribute": {
          "_class": "color",
          "alpha": 1,
          "blue": 1,
          "green": 1,
          "red": 1
        },
        "MSAttributedStringFontAttribute": {
          "_class": "fontDescriptor",
          "attributes": {
            "name": "OpenSans-Bold",
            "size": 18
          }
        },
        "paragraphStyle": {
          "_class": "paragraphStyle",
          "maximumLineHeight": 26,
          "minimumLineHeight": 26
        }
      },
      "verticalAlignment": 0
    },
    "windingRule": 1
  },
  "textBehaviour": 1
}