{
  "_class": "group",
  "booleanOperation": 0,
  "clippingMaskMode": 0,
  "do_objectID": "006E5995-AD9D-449C-BCFA-7B3EFFC3580D",
  "exportOptions": {
    "_class": "exportOptions",
    "exportFormats": [
    ],
    "includedLayerIds": [
    ],
    "layerOptions": 0,
    "shouldTrim": false
  },
  "frame": {
    "_class": "rect",
    "constrainProportions": false,
    "height": 654,
    "width": 320,
    "x": 20,
    "y": 517
  },
  "hasClickThrough": false,
  "hasClippingMask": false,
  "isFixedToViewport": false,
  "isFlippedHorizontal": false,
  "isFlippedVertical": false,
  "isLocked": false,
  "isVisible": true,
  "layerListExpandedType": 2,
  "layers": [
    {
      "class": "text",
      "id": "1E94FEC4-5B7A-4CAE-A622-0B1B428DE5C8"
    },
    {
      "class": "text",
      "id": "06D495AF-EBE9-49A2-B554-13A45BC0B133"
    },
    {
      "class": "text",
      "id": "D5D7D19D-2ABC-4BB6-AB8D-F1212875F390"
    },
    {
      "class": "group",
      "id": "E6859A37-3E44-4C6A-BED5-16B64751B0EB"
    },
    {
      "class": "group",
      "id": "457C992B-0ED9-4693-8FBD-BD0130FE0946"
    },
    {
      "class": "group",
      "id": "1802AE77-4C80-4AD4-BFF8-3C71B3420934"
    },
    {
      "class": "group",
      "id": "CCD1C0D4-9ADA-490F-85DE-8662714EC811"
    },
    {
      "class": "symbolInstance",
      "id": "E1965A24-6B70-4073-8D5F-0EC286DC9949"
    }
  ],
  "name": "Why Us",
  "nameIsFixed": true,
  "resizingConstraint": 63,
  "resizingType": 0,
  "rotation": 0,
  "shouldBreakMaskChain": false,
  "style": {
    "_class": "style",
    "endMarkerType": 0,
    "miterLimit": 10,
    "startMarkerType": 0,
    "windingRule": 1
  }
}