{
  "_class": "group",
  "booleanOperation": 0,
  "clippingMaskMode": 0,
  "do_objectID": "84FDF455-B26E-4F61-B973-8B8F96906112",
  "exportOptions": {
    "_class": "exportOptions",
    "do_objectID": "F196F16C-2825-4584-8AEB-794914FA52F9",
    "exportFormats": [
    ],
    "includedLayerIds": [
    ],
    "layerOptions": 0,
    "shouldTrim": false
  },
  "frame": {
    "_class": "rect",
    "constrainProportions": false,
    "do_objectID": "2CD89D37-083D-416F-9AF2-3F93304F5CB7",
    "height": 35,
    "width": 100,
    "x": 431,
    "y": 27
  },
  "hasClickThrough": false,
  "hasClippingMask": false,
  "isFixedToViewport": false,
  "isFlippedHorizontal": false,
  "isFlippedVertical": false,
  "isLocked": false,
  "isVisible": false,
  "layerListExpandedType": 0,
  "layers": [
    {
      "class": "rectangle",
      "id": "842E6DA6-6AA8-4902-8AA5-3961587453B1"
    },
    {
      "class": "shapeGroup",
      "id": "EBD0BE48-2B83-4B6F-805E-78811035220D"
    },
    {
      "class": "text",
      "id": "65BAB158-A33F-48FA-A2B4-989CDEDB2E0C"
    }
  ],
  "name": "save-campaign",
  "nameIsFixed": true,
  "resizingConstraint": 63,
  "resizingType": 0,
  "rotation": 0,
  "shouldBreakMaskChain": false,
  "style": {
    "_class": "style",
    "do_objectID": "783D2A9F-EDE6-476D-92AB-58FCBB60FC61",
    "endMarkerType": 0,
    "miterLimit": 10,
    "startMarkerType": 0,
    "windingRule": 1
  }
}