{
  "_class": "symbolInstance",
  "booleanOperation": 0,
  "clippingMaskMode": 0,
  "do_objectID": "CCC946E3-1D3C-4FC4-9269-A77B05F686C6",
  "exportOptions": {
    "_class": "exportOptions",
    "do_objectID": "7BBF2A6D-04E2-4355-BA01-D80D6C5DF408",
    "exportFormats": [
    ],
    "includedLayerIds": [
    ],
    "layerOptions": 0,
    "shouldTrim": false
  },
  "frame": {
    "_class": "rect",
    "constrainProportions": false,
    "do_objectID": "4EE9DB63-735D-42B5-BC20-19DFF4133E91",
    "height": 21,
    "width": 87,
    "x": 3,
    "y": 157
  },
  "hasClippingMask": false,
  "horizontalSpacing": 0,
  "isFixedToViewport": false,
  "isFlippedHorizontal": false,
  "isFlippedVertical": false,
  "isLocked": false,
  "isVisible": true,
  "layerListExpandedType": 0,
  "name": "Link / Icon",
  "nameIsFixed": false,
  "overrideValues": [
  ],
  "resizingConstraint": 63,
  "resizingType": 0,
  "rotation": 0,
  "scale": 1,
  "shouldBreakMaskChain": false,
  "style": {
    "_class": "style",
    "do_objectID": "75402138-3249-4014-AA07-A0766863B0BA",
    "endMarkerType": 0,
    "miterLimit": 10,
    "startMarkerType": 0,
    "windingRule": 1
  },
  "symbolID": "C6A4836B-0D17-4CF2-BE8F-52ED5CB82850",
  "verticalSpacing": 0
}