{
  "_class": "text",
  "attributedString": {
    "_class": "attributedString",
    "attributes": [
      {
        "_class": "stringAttribute",
        "attributes": {
          "MSAttributedStringColorAttribute": {
            "_class": "color",
            "alpha": 1,
            "blue": 0.2902374565601349,
            "green": 0.2901752889156342,
            "red": 0.290221631526947
          },
          "MSAttributedStringFontAttribute": {
            "_class": "fontDescriptor",
            "attributes": {
              "name": "OpenSans-Semibold",
              "size": 18
            }
          },
          "paragraphStyle": {
            "_class": "paragraphStyle",
            "alignment": 0
          }
        },
        "length": 21,
        "location": 0
      }
    ],
    "string": "Bantu sebarkan via : "
  },
  "automaticallyDrawOnUnderlyingPath": false,
  "booleanOperation": 0,
  "clippingMaskMode": 0,
  "do_objectID": "4AA97ED7-42D4-4A83-8414-5BAA6615AD39",
  "dontSynchroniseWithSymbol": false,
  "exportOptions": {
    "_class": "exportOptions",
    "do_objectID": "6C1E4BB4-B39C-4AD2-B76E-7BA6293ACD63",
    "exportFormats": [
    ],
    "includedLayerIds": [
    ],
    "layerOptions": 0,
    "shouldTrim": false
  },
  "frame": {
    "_class": "rect",
    "constrainProportions": false,
    "do_objectID": "8457D369-1E92-43EE-9165-0BE9811BB33B",
    "height": 24,
    "width": 182,
    "x": 0,
    "y": 0
  },
  "glyphBounds": "{{1, 5}, {175, 15}}",
  "hasClippingMask": false,
  "isFixedToViewport": false,
  "isFlippedHorizontal": false,
  "isFlippedVertical": false,
  "isLocked": false,
  "isVisible": true,
  "layerListExpandedType": 0,
  "lineSpacingBehaviour": 2,
  "name": "Bantu sebarkan via :",
  "nameIsFixed": false,
  "originalObjectID": "F154E9F7-0D18-4CF1-8403-AF5938F55F82",
  "resizingConstraint": 45,
  "resizingType": 3,
  "rotation": 0,
  "shouldBreakMaskChain": false,
  "style": {
    "_class": "style",
    "blur": {
      "_class": "blur",
      "center": "{0.5, 0.5}",
      "do_objectID": "CBF3DA03-F641-4938-AD92-A3F74DEC5896",
      "isEnabled": false,
      "motionAngle": 0,
      "radius": 11.52,
      "saturation": 1,
      "type": 0
    },
    "do_objectID": "FBA96791-F2C9-4343-8F34-B74EAAB4693F",
    "endMarkerType": 0,
    "miterLimit": 10,
    "startMarkerType": 0,
    "textStyle": {
      "_class": "textStyle",
      "do_objectID": "333C9A55-893E-4417-A7C1-DE82B3B8DA71",
      "encodedAttributes": {
        "MSAttributedStringColorAttribute": {
          "_class": "color",
          "alpha": 1,
          "blue": 0.2902374565601349,
          "green": 0.2901752889156342,
          "red": 0.290221631526947
        },
        "MSAttributedStringFontAttribute": {
          "_class": "fontDescriptor",
          "attributes": {
            "name": "OpenSans-Semibold",
            "size": 18
          }
        },
        "paragraphStyle": {
          "_class": "paragraphStyle",
          "alignment": 0
        }
      },
      "verticalAlignment": 0
    },
    "windingRule": 1
  },
  "textBehaviour": 0,
  "userInfo": {
    "com.animaapp.stc-sketch-plugin": {
      "kModelPropertiesKey": {
        "isAutoWidth": 0
      }
    }
  }
}