{
  "_class": "group",
  "booleanOperation": 0,
  "clippingMaskMode": 0,
  "do_objectID": "5FB443D7-23EB-413B-BB1D-5482603361CC",
  "exportOptions": {
    "_class": "exportOptions",
    "exportFormats": [
    ],
    "includedLayerIds": [
    ],
    "layerOptions": 0,
    "shouldTrim": false
  },
  "frame": {
    "_class": "rect",
    "constrainProportions": false,
    "height": 86,
    "width": 320,
    "x": 20,
    "y": 156
  },
  "hasClickThrough": false,
  "hasClippingMask": false,
  "isFixedToViewport": false,
  "isFlippedHorizontal": false,
  "isFlippedVertical": false,
  "isLocked": false,
  "isVisible": true,
  "layerListExpandedType": 2,
  "layers": [
    {
      "class": "rectangle",
      "id": "4D9F585E-D1F2-4AE4-9156-B083D933FA5D"
    },
    {
      "class": "text",
      "id": "90D4C6C1-C875-4E08-990C-68D66DF0981D"
    },
    {
      "class": "symbolInstance",
      "id": "EF15C962-5788-45C2-AD95-FB0902591D35"
    },
    {
      "class": "text",
      "id": "6A5AF701-3418-4DFF-936B-3229E5BA7805"
    }
  ],
  "name": "donatur-03",
  "nameIsFixed": true,
  "resizingConstraint": 63,
  "resizingType": 0,
  "rotation": 0,
  "shouldBreakMaskChain": false,
  "style": {
    "_class": "style",
    "endMarkerType": 0,
    "miterLimit": 10,
    "startMarkerType": 0,
    "windingRule": 1
  }
}