{
  "_class": "group",
  "booleanOperation": 0,
  "clippingMaskMode": 0,
  "do_objectID": "8F0632A8-B466-4148-8766-C51A9FD2F34C",
  "exportOptions": {
    "_class": "exportOptions",
    "do_objectID": "72EA3AEC-01F6-4431-9B60-B984B65B030A",
    "exportFormats": [
    ],
    "includedLayerIds": [
    ],
    "layerOptions": 0,
    "shouldTrim": false
  },
  "frame": {
    "_class": "rect",
    "constrainProportions": false,
    "do_objectID": "1E6CBF06-239E-4712-ABA2-81CF86110798",
    "height": 24,
    "width": 24,
    "x": 53,
    "y": 0
  },
  "hasClickThrough": false,
  "hasClippingMask": false,
  "isFixedToViewport": false,
  "isFlippedHorizontal": false,
  "isFlippedVertical": false,
  "isLocked": false,
  "isVisible": true,
  "layerListExpandedType": 0,
  "layers": [
    {
      "class": "oval",
      "id": "0631A6DB-5B0D-454A-AFD5-0EED2EADA420"
    },
    {
      "class": "shapePath",
      "id": "9FF7C62F-3D53-43AF-98DD-364CD309EE68"
    }
  ],
  "name": "Twitter",
  "nameIsFixed": true,
  "resizingConstraint": 63,
  "resizingType": 0,
  "rotation": 0,
  "shouldBreakMaskChain": false,
  "style": {
    "_class": "style",
    "blur": {
      "_class": "blur",
      "center": "{0.5, 0.5}",
      "do_objectID": "D32CA10E-F2DD-4458-9DAB-494F7B90CB51",
      "isEnabled": false,
      "motionAngle": 0,
      "radius": 3.456,
      "saturation": 1,
      "type": 0
    },
    "do_objectID": "88232707-14DC-464B-831A-4E1A6C191F6E",
    "endMarkerType": 0,
    "miterLimit": 10,
    "startMarkerType": 0,
    "windingRule": 1
  },
  "userInfo": {
    "com.animaapp.stc-sketch-plugin": {
      "kModelPropertiesKey": {
      }
    }
  }
}