{
  "_class": "group",
  "booleanOperation": 0,
  "clippingMaskMode": 0,
  "do_objectID": "F5CB7F0F-79BA-4EA8-B0FA-FA959EB594F8",
  "exportOptions": {
    "_class": "exportOptions",
    "do_objectID": "FCCD3020-3B51-45D5-B7A5-F15434415E54",
    "exportFormats": [
    ],
    "includedLayerIds": [
    ],
    "layerOptions": 0,
    "shouldTrim": false
  },
  "frame": {
    "_class": "rect",
    "constrainProportions": false,
    "do_objectID": "295BD6AB-0F6F-4056-BB75-E7087D4E089B",
    "height": 270,
    "width": 530,
    "x": 85,
    "y": 299
  },
  "hasClickThrough": false,
  "hasClippingMask": false,
  "isFixedToViewport": false,
  "isFlippedHorizontal": false,
  "isFlippedVertical": false,
  "isLocked": false,
  "isVisible": true,
  "layerListExpandedType": 2,
  "layers": [
    {
      "class": "rectangle",
      "id": "77C1803C-471A-4963-905D-568E07B3494F"
    },
    {
      "class": "bitmap",
      "id": "B3BFF48E-482A-4A85-B08A-A16A26C90DC7"
    },
    {
      "class": "rectangle",
      "id": "A7F39339-C9EF-44B3-BFB5-7609A866FE26"
    },
    {
      "class": "text",
      "id": "6ACDB1E9-D4D0-4679-A64D-8A6BE1339C57"
    }
  ],
  "name": "photo-1443304895043-ef30921332c5",
  "nameIsFixed": false,
  "resizingConstraint": 63,
  "resizingType": 0,
  "rotation": 0,
  "shouldBreakMaskChain": false,
  "style": {
    "_class": "style",
    "do_objectID": "47109E3B-D0CA-4A66-9749-ABBB121B4CFD",
    "endMarkerType": 0,
    "miterLimit": 10,
    "startMarkerType": 0,
    "windingRule": 1
  }
}