{
  "_class": "group",
  "booleanOperation": 0,
  "clippingMaskMode": 0,
  "do_objectID": "06C9D76D-9727-4674-BD65-C391A565386D",
  "exportOptions": {
    "_class": "exportOptions",
    "exportFormats": [
    ],
    "includedLayerIds": [
    ],
    "layerOptions": 0,
    "shouldTrim": false
  },
  "frame": {
    "_class": "rect",
    "constrainProportions": false,
    "height": 125,
    "width": 400,
    "x": 40,
    "y": 263
  },
  "hasClickThrough": false,
  "hasClippingMask": false,
  "isFixedToViewport": false,
  "isFlippedHorizontal": false,
  "isFlippedVertical": false,
  "isLocked": false,
  "isVisible": true,
  "layerListExpandedType": 0,
  "layers": [
    {
      "class": "text",
      "id": "9FBBCB37-3738-4534-A4CC-709BE0F14D7A"
    },
    {
      "class": "group",
      "id": "221ACD9F-6B89-4E9D-88EF-3790B8BF6C1F"
    },
    {
      "class": "shapePath",
      "id": "79364A58-5F9F-4E5E-ADDC-B21AC17EED2C"
    },
    {
      "class": "text",
      "id": "F4C42333-6E43-42C0-9AC1-A6DEB7B6458B"
    }
  ],
  "name": "Group 5",
  "nameIsFixed": false,
  "resizingConstraint": 63,
  "resizingType": 0,
  "rotation": 0,
  "shouldBreakMaskChain": false,
  "style": {
    "_class": "style",
    "endMarkerType": 0,
    "miterLimit": 10,
    "startMarkerType": 0,
    "windingRule": 1
  }
}