{
  "_class": "group",
  "booleanOperation": 0,
  "clippingMaskMode": 0,
  "do_objectID": "92C811C5-8EC2-47FD-90A4-C194440000AA",
  "exportOptions": {
    "_class": "exportOptions",
    "do_objectID": "69CC1311-A18E-4B9D-B239-79857A5B6690",
    "exportFormats": [
    ],
    "includedLayerIds": [
    ],
    "layerOptions": 0,
    "shouldTrim": false
  },
  "frame": {
    "_class": "rect",
    "constrainProportions": false,
    "do_objectID": "82D57FE7-FE26-4607-9433-282E11CE33A2",
    "height": 143,
    "width": 283,
    "x": 17,
    "y": 201
  },
  "hasClickThrough": false,
  "hasClippingMask": false,
  "isFixedToViewport": false,
  "isFlippedHorizontal": false,
  "isFlippedVertical": false,
  "isLocked": false,
  "isVisible": true,
  "layerListExpandedType": 0,
  "layers": [
    {
      "class": "text",
      "id": "76256C88-3AF5-4082-BC57-33339CD748EE"
    },
    {
      "class": "text",
      "id": "74E47A12-9BA0-4722-A72F-0A2878F09EB9"
    },
    {
      "class": "group",
      "id": "26779F22-A907-4CCC-BF65-44D1AF00A8F0"
    },
    {
      "class": "text",
      "id": "ACFE7F9F-18BB-481F-9911-A8DDA4899784"
    },
    {
      "class": "text",
      "id": "79702B48-F8D8-49F5-B029-17064A5417C1"
    },
    {
      "class": "text",
      "id": "CD95B02E-8CAE-4D2C-92E5-79AEC6EE0C83"
    },
    {
      "class": "text",
      "id": "CA1BC199-B9FB-4900-8D62-7C8FD9E005E3"
    },
    {
      "class": "rectangle",
      "id": "E5FDA6B5-738E-4902-8EEE-9CB6DAF6C9D6"
    },
    {
      "class": "rectangle",
      "id": "FBED83ED-15F0-49BA-B131-B8F7CCFAC0DB"
    }
  ],
  "name": "Group 3",
  "nameIsFixed": false,
  "originalObjectID": "AE8F1CB7-92CE-4CB5-A947-354B3A4F5F00",
  "resizingConstraint": 63,
  "resizingType": 0,
  "rotation": 0,
  "shouldBreakMaskChain": false,
  "style": {
    "_class": "style",
    "do_objectID": "778E12A5-106C-4F96-BE7F-D80F4CCE2217",
    "endMarkerType": 0,
    "miterLimit": 10,
    "startMarkerType": 0,
    "windingRule": 1
  },
  "userInfo": {
    "com.animaapp.stc-sketch-plugin": {
      "kModelPropertiesKey": {
      }
    }
  }
}