{
  "_class": "group",
  "booleanOperation": 0,
  "clippingMaskMode": 0,
  "do_objectID": "3B413018-97BB-420D-B6A4-577FD0BDAB9B",
  "exportOptions": {
    "_class": "exportOptions",
    "do_objectID": "AE1398BD-0906-4B7C-B31F-2F1F5E8FD09C",
    "exportFormats": [
    ],
    "includedLayerIds": [
    ],
    "layerOptions": 0,
    "shouldTrim": false
  },
  "frame": {
    "_class": "rect",
    "constrainProportions": false,
    "do_objectID": "CFF23CD8-8333-4BF3-A806-3BD083C8DB7B",
    "height": 570,
    "width": 1280,
    "x": 0,
    "y": 1546
  },
  "hasClickThrough": false,
  "hasClippingMask": false,
  "isFixedToViewport": false,
  "isFlippedHorizontal": false,
  "isFlippedVertical": false,
  "isLocked": false,
  "isVisible": true,
  "layerListExpandedType": 0,
  "layers": [
    {
      "class": "rectangle",
      "id": "E688E499-AE23-4387-8E7E-668230537095"
    },
    {
      "class": "rectangle",
      "id": "92E11CE6-AF7C-4453-A5E9-46A66FE266AA"
    },
    {
      "class": "group",
      "id": "21A7A02D-D2DE-437A-A721-5C4675710B5F"
    },
    {
      "class": "group",
      "id": "228A53A1-2DB5-466D-9B98-2D4581CF4E2A"
    },
    {
      "class": "text",
      "id": "1DDECA67-3D8A-4514-8789-FDCEA904978A"
    },
    {
      "class": "text",
      "id": "25417E16-0709-4C14-96E1-25A8AB0B56A2"
    },
    {
      "class": "group",
      "id": "82463E9D-2870-4F37-B2E1-364D14B8EBC3"
    },
    {
      "class": "group",
      "id": "BBE437DE-3E7E-4DF3-8131-C49237A8753C"
    },
    {
      "class": "group",
      "id": "202A6176-2F81-4E97-81DD-D02FEB819E4B"
    },
    {
      "class": "group",
      "id": "FECF6E6B-4811-4858-B2AA-A147C3A23F95"
    },
    {
      "class": "group",
      "id": "237AFFA2-6D96-4393-8F36-8538B9340D59"
    }
  ],
  "name": "footer",
  "nameIsFixed": true,
  "resizingConstraint": 63,
  "resizingType": 0,
  "rotation": 0,
  "shouldBreakMaskChain": false,
  "style": {
    "_class": "style",
    "do_objectID": "54C126CA-54A2-48B4-A182-93B6CD48FB12",
    "endMarkerType": 0,
    "miterLimit": 10,
    "startMarkerType": 0,
    "windingRule": 1
  }
}