{
  "_class": "group",
  "booleanOperation": 0,
  "clippingMaskMode": 0,
  "do_objectID": "0365331A-89ED-444C-B6DD-462EA1CFA93B",
  "exportOptions": {
    "_class": "exportOptions",
    "exportFormats": [
    ],
    "includedLayerIds": [
    ],
    "layerOptions": 0,
    "shouldTrim": false
  },
  "frame": {
    "_class": "rect",
    "constrainProportions": false,
    "height": 467,
    "width": 360,
    "x": 0,
    "y": 1957
  },
  "hasClickThrough": false,
  "hasClippingMask": false,
  "isFixedToViewport": false,
  "isFlippedHorizontal": false,
  "isFlippedVertical": false,
  "isLocked": false,
  "isVisible": false,
  "layerListExpandedType": 0,
  "layers": [
    {
      "class": "group",
      "id": "1A41E529-82D5-426D-8FD5-8E1A238B02E9"
    },
    {
      "class": "group",
      "id": "A4767DEA-5410-471A-97D1-6B9890158DFA"
    },
    {
      "class": "group",
      "id": "2D0917AB-4CCB-49BA-A367-A7190C72774B"
    },
    {
      "class": "text",
      "id": "1F67FF18-427B-4E51-98AF-3B6D3D430C4A"
    },
    {
      "class": "symbolInstance",
      "id": "C7F42986-0242-40BD-9531-1CD3D8D32A43"
    },
    {
      "class": "text",
      "id": "411C0CD4-17F4-4E04-9C2E-668B698C1DB2"
    },
    {
      "class": "rectangle",
      "id": "EECC1D75-5432-4955-A83F-AE4E2D046CA0"
    },
    {
      "class": "rectangle",
      "id": "F5590797-E318-4905-B017-029240F63326"
    }
  ],
  "name": "Fundraiser",
  "nameIsFixed": true,
  "resizingConstraint": 63,
  "resizingType": 0,
  "rotation": 0,
  "shouldBreakMaskChain": false,
  "style": {
    "_class": "style",
    "endMarkerType": 0,
    "miterLimit": 10,
    "startMarkerType": 0,
    "windingRule": 1
  }
}